shopagent/__init__.py
shopagent/api/__init__.py
shopagent/api/api.py
shopagent/api/arguments.py
shopagent/api/code_examples.py
shopagent/api/description.py
shopagent/api/fields_and_connections.py
shopagent/api/first_list.py
shopagent/api/list.py
shopagent/api/mutation.py
shopagent/api/object.py
shopagent/api/possible_second_list.py
shopagent/api/query.py
shopagent/api/returns.py
shopagent/api/second_list.py
shopagent/api/third_list.py
shopagent/code_gen/__init__.py
shopagent/code_gen/code_gen.py
shopagent/constants/__init__.py
shopagent/constants/constants.py
shopagent/lsd/__init__.py
shopagent/lsd/lsd.py
shopagent/models/__init__.py
shopagent/models/api.py
shopagent/models/nav.py
shopagent/nav/__init__.py
shopagent/nav/nav.py
shopagent-1.0.1.data/data/data/shopify_api.json
shopagent-1.0.1.dist-info/licenses/LICENSE.txt
shopagent-1.0.1.dist-info/METADATA
shopagent-1.0.1.dist-info/WHEEL
shopagent-1.0.1.dist-info/top_level.txt
shopagent-1.0.1.dist-info/RECORD
